<annotation>
	<folder>resized_img</folder>
	<filename>road276.png</filename>
	<path>C:\Users\vasyl\Desktop\resized_img\road276.png</path>
	<source>
		<database>Unknown</database>
	</source>
	<size>
		<width>400</width>
		<height>300</height>
		<depth>3</depth>
	</size>
	<segmented>0</segmented>
	<object>
		<name>trafficlight_red</name>
		<pose>Unspecified</pose>
		<truncated>0</truncated>
		<difficult>0</difficult>
		<bndbox>
			<xmin>115</xmin>
			<ymin>62</ymin>
			<xmax>133</xmax>
			<ymax>101</ymax>
		</bndbox>
	</object>
	<object>
		<name>trafficlight_red</name>
		<pose>Unspecified</pose>
		<truncated>0</truncated>
		<difficult>0</difficult>
		<bndbox>
			<xmin>46</xmin>
			<ymin>44</ymin>
			<xmax>69</xmax>
			<ymax>86</ymax>
		</bndbox>
	</object>
</annotation>
